{
    "match": [
        {
            "match_name": "England vs New Zealand, 1st Match",
            "url": "75413/eng-vs-nz-1st-match-icc-cricket-world-cup-2023",
            "team1_name": "England",
            "team1_score": "282",
            "team2_name": "New Zealand",
            "team2_score": "283",
            "players": {
                "6507": {
                    "pid": "6507",
                    "name": "Bairstow",
                    "team_name": "",
                    "out_by": "c Daryl Mitchell b Santner",
                    "runs_scored": "33",
                    "balls_faced": "35",
                    "fours": "4",
                    "sixes": "1",
                    "strike_rate": "94.29",
                    "overs": "0",
                    "maiden": "0",
                    "runs_given": "0",
                    "wickets": "0",
                    "no_balls": "0",
                    "wide_balls": "0",
                    "CROST": "0",
                    "extras": "0"
                },
                "6660": {
                    "pid": "6660",
                    "name": "Malan",
                    "team_name": "",
                    "out_by": "c Latham b Matt Henry",
                    "runs_scored": "14",
                    "balls_faced": "24",
                    "fours": "2",
                    "sixes": "0",
                    "strike_rate": "58.33",
                    "overs": "0",
                    "maiden": "0",
                    "runs_given": "0",
                    "wickets": "0",
                    "no_balls": "0",
                    "wide_balls": "0",
                    "CROST": "0",
                    "extras": "0"
                },
                "8019": {
                    "pid": "8019",
                    "name": "Root",
                    "team_name": "",
                    "out_by": "b Glenn Phillips",
                    "runs_scored": "77",
                    "balls_faced": "86",
                    "fours": "4",
                    "sixes": "1",
                    "strike_rate": "89.53",
                    "overs": "0",
                    "maiden": "0",
                    "runs_given": "0",
                    "wickets": "0",
                    "no_balls": "0",
                    "wide_balls": "0",
                    "CROST": "0",
                    "extras": "0"
                },
                "12201": {
                    "pid": "12201",
                    "name": "Harry Brook",
                    "team_name": "",
                    "out_by": "c Conway b Rachin Ravindra",
                    "runs_scored": "25",
                    "balls_faced": "16",
                    "fours": "4",
                    "sixes": "1",
                    "strike_rate": "156.25",
                    "overs": "0",
                    "maiden": "0",
                    "runs_given": "0",
                    "wickets": "0",
                    "no_balls": "0",
                    "wide_balls": "0",
                    "CROST": "0",
                    "extras": "0"
                },
                "2258": {
                    "pid": "2258",
                    "name": "Jos Buttler",
                    "team_name": "",
                    "out_by": "c Latham b Matt Henry",
                    "runs_scored": "43",
                    "balls_faced": "42",
                    "fours": "2",
                    "sixes": "2",
                    "strike_rate": "102.38",
                    "overs": "0",
                    "maiden": "0",
                    "runs_given": "0",
                    "wickets": "0",
                    "no_balls": "0",
                    "wide_balls": "0",
                    "CROST": "0",
                    "extras": "0"
                },
                "10045": {
                    "pid": "10045",
                    "name": "Livingstone",
                    "team_name": "",
                    "out_by": "c Matt Henry b Boult",
                    "runs_scored": "20",
                    "balls_faced": "22",
                    "fours": "3",
                    "sixes": "0",
                    "strike_rate": "90.91",
                    "overs": "0",
                    "maiden": "0",
                    "runs_given": "0",
                    "wickets": "0",
                    "no_balls": "0",
                    "wide_balls": "0",
                    "CROST": "0",
                    "extras": "0"
                },
                "6692": {
                    "pid": "6692",
                    "name": "Moeen",
                    "team_name": "",
                    "out_by": "b Glenn Phillips",
                    "runs_scored": "11",
                    "balls_faced": "17",
                    "fours": "1",
                    "sixes": "0",
                    "strike_rate": "64.71",
                    "overs": "0",
                    "maiden": "0",
                    "runs_given": "0",
                    "wickets": "0",
                    "no_balls": "0",
                    "wide_balls": "0",
                    "CROST": "0",
                    "extras": "0"
                },
                "10420": {
                    "pid": "10420",
                    "name": "Sam Curran",
                    "team_name": "",
                    "out_by": "c Latham b Matt Henry",
                    "runs_scored": "14",
                    "balls_faced": "19",
                    "fours": "0",
                    "sixes": "0",
                    "strike_rate": "73.68",
                    "overs": "0",
                    "maiden": "0",
                    "runs_given": "0",
                    "wickets": "0",
                    "no_balls": "0",
                    "wide_balls": "0",
                    "CROST": "0",
                    "extras": "0"
                },
                "6670": {
                    "pid": "6670",
                    "name": "Chris Woakes",
                    "team_name": "",
                    "out_by": "c Will Young b Santner",
                    "runs_scored": "11",
                    "balls_faced": "12",
                    "fours": "1",
                    "sixes": "0",
                    "strike_rate": "91.67",
                    "overs": "0",
                    "maiden": "0",
                    "runs_given": "0",
                    "wickets": "0",
                    "no_balls": "0",
                    "wide_balls": "0",
                    "CROST": "0",
                    "extras": "0"
                },
                "1742": {
                    "pid": "1742",
                    "name": "Adil Rashid",
                    "team_name": "",
                    "out_by": "not out",
                    "runs_scored": "15",
                    "balls_faced": "13",
                    "fours": "0",
                    "sixes": "1",
                    "strike_rate": "115.38",
                    "overs": "0",
                    "maiden": "0",
                    "runs_given": "0",
                    "wickets": "0",
                    "no_balls": "0",
                    "wide_balls": "0",
                    "CROST": "0",
                    "extras": "0"
                },
                "8383": {
                    "pid": "8383",
                    "name": "Mark Wood",
                    "team_name": "",
                    "out_by": "not out",
                    "runs_scored": "13",
                    "balls_faced": "14",
                    "fours": "0",
                    "sixes": "0",
                    "strike_rate": "92.86",
                    "overs": "0",
                    "maiden": "0",
                    "runs_given": "0",
                    "wickets": "0",
                    "no_balls": "0",
                    "wide_balls": "0",
                    "CROST": "0",
                    "extras": "0"
                },
                "5446": {
                    "pid": "0",
                    "name": "",
                    "team_name": "",
                    "out_by": "None",
                    "runs_scored": "-1",
                    "balls_faced": "0",
                    "fours": "0",
                    "sixes": "0",
                    "strike_rate": "0",
                    "overs": "0",
                    "maiden": "0",
                    "runs_given": "0",
                    "wickets": "0",
                    "no_balls": "0",
                    "wide_balls": "0",
                    "CROST": "0",
                    "extras": "0"
                },
                "50334": {
                    "pid": "0",
                    "name": "",
                    "team_name": "",
                    "out_by": "None",
                    "runs_scored": "-1",
                    "balls_faced": "0",
                    "fours": "0",
                    "sixes": "0",
                    "strike_rate": "0",
                    "overs": "0",
                    "maiden": "0",
                    "runs_given": "0",
                    "wickets": "0",
                    "no_balls": "0",
                    "wide_balls": "0",
                    "CROST": "0",
                    "extras": "0"
                },
                "50341": {
                    "pid": "0",
                    "name": "",
                    "team_name": "",
                    "out_by": "None",
                    "runs_scored": "-1",
                    "balls_faced": "0",
                    "fours": "0",
                    "sixes": "0",
                    "strike_rate": "0",
                    "overs": "0",
                    "maiden": "0",
                    "runs_given": "0",
                    "wickets": "0",
                    "no_balls": "0",
                    "wide_balls": "0",
                    "CROST": "0",
                    "extras": "0"
                }
            }
        }
    ]
}